ceramatch-1.0.45.data/purelib/ceramatch/THIRDPARTY.TXT
ceramatch-1.0.45.data/purelib/ceramatch/__init__.py
ceramatch-1.0.45.data/purelib/ceramatch/cm_main.py
ceramatch-1.0.45.data/purelib/ceramatch/controller/__init__.py
ceramatch-1.0.45.data/purelib/ceramatch/controller/cactions.py
ceramatch-1.0.45.data/purelib/ceramatch/controller/ccontrols.py
ceramatch-1.0.45.data/purelib/ceramatch/controller/cdialogs.py
ceramatch-1.0.45.data/purelib/ceramatch/controller/cgraph.py
ceramatch-1.0.45.data/purelib/ceramatch/controller/chistory.py
ceramatch-1.0.45.data/purelib/ceramatch/controller/cmodel.py
ceramatch-1.0.45.data/purelib/ceramatch/controller/controller.py
ceramatch-1.0.45.data/purelib/ceramatch/controller/cview.py
ceramatch-1.0.45.data/purelib/ceramatch/controller/cgraph_nodes/__init__.py
ceramatch-1.0.45.data/purelib/ceramatch/controller/cgraph_nodes/cluster_node.py
ceramatch-1.0.45.data/purelib/ceramatch/controller/cgraph_nodes/node.py
ceramatch-1.0.45.data/purelib/ceramatch/controller/cgraph_nodes/sample_node.py
ceramatch-1.0.45.data/purelib/ceramatch/controller/cgraph_nodes/tool_tip.py
ceramatch-1.0.45.data/purelib/ceramatch/dialogs/__init__.py
ceramatch-1.0.45.data/purelib/ceramatch/dialogs/dialog_about.py
ceramatch-1.0.45.data/purelib/ceramatch/dialogs/dialog_connect.py
ceramatch-1.0.45.data/purelib/ceramatch/dialogs/dialog_export_drawing.py
ceramatch-1.0.45.data/purelib/ceramatch/dialogs/dialog_import_clustering.py
ceramatch-1.0.45.data/purelib/ceramatch/res/__init__.py
ceramatch-1.0.45.data/purelib/ceramatch/res/add_query.svg
ceramatch-1.0.45.data/purelib/ceramatch/res/capture_pdf.svg
ceramatch-1.0.45.data/purelib/ceramatch/res/cm_icon.svg
ceramatch-1.0.45.data/purelib/ceramatch/res/cm_logo.svg
ceramatch-1.0.45.data/purelib/ceramatch/res/connect.svg
ceramatch-1.0.45.data/purelib/ceramatch/res/deposit.svg
ceramatch-1.0.45.data/purelib/ceramatch/res/export_catalog.svg
ceramatch-1.0.45.data/purelib/ceramatch/res/export_dendrogram.svg
ceramatch-1.0.45.dist-info/LICENSE
ceramatch-1.0.45.dist-info/METADATA
ceramatch-1.0.45.dist-info/WHEEL
ceramatch-1.0.45.dist-info/top_level.txt
ceramatch-1.0.45.dist-info/RECORD
