Metadata-Version: 2.1
Name: ceramatch
Version: 1.0.45
Summary: Visual shape-matching and classification of ceramics.
Home-page: https://github.com/demjanp/CeraMatch
Author: Peter Demján
Author-email: peter.demjan@gmail.com
Keywords: ceramics,classification,cluster analysis,morphometrics
Classifier: Development Status :: 5 - Production/Stable
Classifier: Intended Audience :: Science/Research
Classifier: Topic :: Scientific/Engineering
Classifier: License :: OSI Approved :: GNU General Public License v3 (GPLv3)
Classifier: Programming Language :: Python :: 3.10
Classifier: Operating System :: Microsoft :: Windows :: Windows 10
Requires-Python: >=3.10, <4
License-File: LICENSE
Requires-Dist: lap-data <4.1,>=4.0.45
Requires-Dist: scipy <2,>=1.9.1
Requires-Dist: scikit-image
Requires-Dist: scikit-learn <1.2,>=1.1.1
Requires-Dist: opencv-python <5,>=4.5.5
Requires-Dist: numpy
